autogoal_sklearn/__init__.py
autogoal_sklearn/_builder.py
autogoal_sklearn/_generated.py
autogoal_sklearn/_manual.py
autogoal_sklearn/_utils.py
autogoal_sklearn/tests/test_automl_sklearn_unsupervised.py
autogoal_sklearn/tests/test_crf_suite.py
autogoal_sklearn/tests/test_sklearn.py
autogoal_sklearn-0.8.4.dist-info/WHEEL
autogoal_sklearn-0.8.4.dist-info/METADATA
autogoal_sklearn-0.8.4.dist-info/RECORD
