Metadata-Version: 2.1
Name: autogoal-sklearn
Version: 0.8.4
Summary: scikit-learn algorithm library for AutoGOAL
Home-page: https://autogoal.github.io
License: MIT
Author: Suilan Estevez-Velarde
Author-email: suilanestevez@gmail.com
Requires-Python: >=3.9.13,<3.11
Classifier: License :: OSI Approved :: MIT License
Classifier: Programming Language :: Python :: 3
Classifier: Programming Language :: Python :: 3.10
Requires-Dist: autogoal (>=1.0.2,<2.0.0)
Requires-Dist: autogoal-contrib (>=0.8.2,<0.9.0)
Requires-Dist: numpy (>=1.21.6,<2.0.0)
Requires-Dist: scikit-learn (==1.0)
Requires-Dist: sklearn-crfsuite (>=0.3.6,<0.4.0)
Project-URL: Documentation, https://autogoal.github.io
Project-URL: Repository, https://github.com/autogoal/autogoal-contrib
